hyperfusion/__init__.py
hyperfusion/_version.py
hyperfusion/binaries/__init__.py
hyperfusion/binaries/hyperfusion
hyperfusion/binaries/hyperfusion-linux-x86_64
hyperfusion/cli/__init__.py
hyperfusion/cli/main.py
hyperfusion/service/__init__.py
hyperfusion/service/bus.py
hyperfusion/service/exec.py
hyperfusion/service/grpc_service.py
hyperfusion/service/hyperfusion_pb2.py
hyperfusion/service/hyperfusion_pb2_grpc.py
hyperfusion/service/ipc.py
hyperfusion/service/logger.py
hyperfusion/service/main_service.py
hyperfusion/service/messages.py
hyperfusion/service/protocol.py
hyperfusion/service/runner.py
hyperfusion/service/udtf_loader.py
hyperfusion/udtf/__init__.py
hyperfusion/udtf/decorator.py
hyperfusion/udtf/registry.py
hyperfusion/udtf/conversion/__init__.py
hyperfusion/udtf/conversion/dataframe_converter.py
hyperfusion/udtf/conversion/input_converter.py
hyperfusion/udtf/conversion/output_converter.py
hyperfusion/udtf/error_handling/__init__.py
hyperfusion/udtf/error_handling/error_schemas.py
hyperfusion/udtf/error_handling/exceptions.py
hyperfusion/udtf/processing/__init__.py
hyperfusion/udtf/processing/batch_processor.py
hyperfusion/udtf/processing/executor.py
hyperfusion/udtf/processing/mode_detection.py
hyperfusion/udtf/processing/record_processor.py
hyperfusion/udtf/schema/__init__.py
hyperfusion/udtf/schema/inference.py
hyperfusion/udtf/schema/mapping.py
hyperfusion/udtf/schema/validation.py
hyperfusion/udtf/utils/__init__.py
hyperfusion/udtf/utils/arrow_utils.py
hyperfusion/udtf/utils/type_utils.py
hyperfusion-0.1.8.dist-info/licenses/LICENSE
hyperfusion-0.1.8.dist-info/METADATA
hyperfusion-0.1.8.dist-info/WHEEL
hyperfusion-0.1.8.dist-info/entry_points.txt
hyperfusion-0.1.8.dist-info/top_level.txt
hyperfusion-0.1.8.dist-info/RECORD
