Metadata-Version: 2.4
Name: hyperfusion
Version: 0.1.8
Summary: High-performance SQL execution engine with UDTF support
License: MIT
Project-URL: Homepage, https://github.com/hyperdance/hyperfusion
Project-URL: Repository, https://github.com/hyperdance/hyperfusion
Requires-Python: >=3.8
License-File: LICENSE
Requires-Dist: grpcio>=1.50.0
Requires-Dist: grpcio-tools>=1.50.0
Requires-Dist: pyarrow>=10.0.0
Requires-Dist: click>=8.0.0
Requires-Dist: asyncio
Requires-Dist: pandas>=2.0.0
Requires-Dist: polars>=0.20.0
Requires-Dist: numpy>=1.20.0
Requires-Dist: aiohttp>=3.8.0
Dynamic: license-file
